{
  "attributes": {
    "input": {
      "attributes": {
        "values": [
          {
            "attributes": {
              "name": "firstname"
            },
            "type": "identityAttribute"
          },
          {
            "attributes": {
              "begin": 0,
              "end": 1,
              "input": {
                "attributes": {
                  "name": "lastname"
                },
                "type": "identityAttribute"
              }
            },
            "type": "substring"
          }
        ]
      },
      "type": "concat"
    }
  },
  "id": "7ce50649-7517-4d25-893b-430f0420576f",
  "internal": false,
  "name": "DeriveFirstNameLastInitial",
  "type": "upper"
},
    "internal": false,
    "name": "DeriveFirstNameLastInitial",
    "type": "upper"
  }